main.py
cc_tpm_tools-0.1.1.dist-info/METADATA
cc_tpm_tools-0.1.1.dist-info/WHEEL
cc_tpm_tools-0.1.1.dist-info/entry_points.txt
cc_tpm_tools-0.1.1.dist-info/top_level.txt
cc_tpm_tools-0.1.1.dist-info/RECORD
