Metadata-Version: 2.4
Name: cc-tpm-tools
Version: 0.1.1
Summary: CLI and Python tools for CC-TPM.
Project-URL: Homepage, https://github.com/Deleranax/tpm
Project-URL: Issues, https://github.com/Deleranax/tpm/issues
Requires-Python: >=3.12
Requires-Dist: typer-slim>=0.15
Requires-Dist: click<8.2
